zmarketo/__init__.py
zmarketo/version.py
zmarketo/zmarketo.py
zmarketo-0.2.7.dist-info/DESCRIPTION.rst
zmarketo-0.2.7.dist-info/METADATA
zmarketo-0.2.7.dist-info/RECORD
zmarketo-0.2.7.dist-info/WHEEL
zmarketo-0.2.7.dist-info/metadata.json
zmarketo-0.2.7.dist-info/top_level.txt
