Metadata-Version: 2.0
Name: zmarketo
Version: 0.2.7
Summary: marketo-py is an api wrapper aroung the Marketo Rest API.
Home-page: https://github.com/zenefits/zmarketo
Author: Zenefits.com
Author-email: bzindler@zenefits.com
License: MIT License
Platform: UNKNOWN
Requires-Dist: requests
